[
  {
    "movie": "Pre Historic Adventure [7D | English 7D]",
    "rawTitle": "Pre Historic Adventure",
    "lang": "English 7D",
    "format": "7D",
    "venue": "9D Theatre: Grand Mall, Raigarh",
    "chain": "Vision Engineering & Technology",
    "city": "Unknown",
    "state": "Unknown",
    "time": "2026-06-21 08:00 PM",
    "audi": "",
    "sessionId": "21197",
    "totalSeats": 12,
    "availableSeats": 12,
    "soldSeats": 0,
    "grossRevenue": 0,
    "source": "BMS",
    "availStatus": 1
  },
  {
    "movie": "Temple Run [7D | English 7D]",
    "rawTitle": "Temple Run",
    "lang": "English 7D",
    "format": "7D",
    "venue": "9D Theatre: Grand Mall, Raigarh",
    "chain": "Vision Engineering & Technology",
    "city": "Unknown",
    "state": "Unknown",
    "time": "2026-06-21 08:30 PM",
    "audi": "",
    "sessionId": "20831",
    "totalSeats": 12,
    "availableSeats": 12,
    "soldSeats": 0,
    "grossRevenue": 0,
    "source": "BMS",
    "availStatus": 1
  },
  {
    "movie": "The House of Dead (7D) [7D | English]",
    "rawTitle": "The House of Dead (7D)",
    "lang": "English",
    "format": "7D",
    "venue": "9D Theatre: Grand Mall, Raigarh",
    "chain": "Vision Engineering & Technology",
    "city": "Unknown",
    "state": "Unknown",
    "time": "2026-06-21 09:00 PM",
    "audi": "",
    "sessionId": "21075",
    "totalSeats": 12,
    "availableSeats": 12,
    "soldSeats": 0,
    "grossRevenue": 0,
    "source": "BMS",
    "availStatus": 1
  },
  {
    "movie": "The House of Dead (7D) [7D | English]",
    "rawTitle": "The House of Dead (7D)",
    "lang": "English",
    "format": "7D",
    "venue": "9D Theatre: Grand Mall, Raigarh",
    "chain": "Vision Engineering & Technology",
    "city": "Unknown",
    "state": "Unknown",
    "time": "2026-06-21 09:30 PM",
    "audi": "",
    "sessionId": "20953",
    "totalSeats": 12,
    "availableSeats": 12,
    "soldSeats": 0,
    "grossRevenue": 0,
    "source": "BMS",
    "availStatus": 1
  },
  {
    "movie": "Cocktail 2 [2D | Hindi]",
    "rawTitle": "Cocktail 2",
    "lang": "Hindi",
    "format": "2D",
    "venue": "Cineplexx: Beside Hotel Deepti, Rourkela",
    "chain": "Cineplexx",
    "city": "Unknown",
    "state": "Unknown",
    "time": "2026-06-21 09:20 PM",
    "audi": "DOLBY 7.1",
    "sessionId": "13016",
    "totalSeats": 178,
    "availableSeats": 178,
    "soldSeats": 0,
    "grossRevenue": 0,
    "source": "BMS",
    "availStatus": 1
  },
  {
    "movie": "Haunted Echoes of the Past [3D | Hindi]",
    "rawTitle": "Haunted Echoes of the Past",
    "lang": "Hindi",
    "format": "3D",
    "venue": "Cineplexx: Beside Hotel Deepti, Rourkela",
    "chain": "Cineplexx",
    "city": "Unknown",
    "state": "Unknown",
    "time": "2026-06-21 10:00 PM",
    "audi": "DOLBY 7.1",
    "sessionId": "13057",
    "totalSeats": 177,
    "availableSeats": 177,
    "soldSeats": 0,
    "grossRevenue": 0,
    "source": "BMS",
    "availStatus": 1
  },
  {
    "movie": "Main Vaapas Aaunga [2D | Hindi]",
    "rawTitle": "Main Vaapas Aaunga",
    "lang": "Hindi",
    "format": "2D",
    "venue": "Cineplexx: Beside Hotel Deepti, Rourkela",
    "chain": "Cineplexx",
    "city": "Unknown",
    "state": "Unknown",
    "time": "2026-06-21 09:00 PM",
    "audi": "DOLBY 7.1",
    "sessionId": "13072",
    "totalSeats": 153,
    "availableSeats": 153,
    "soldSeats": 0,
    "grossRevenue": 0,
    "source": "BMS",
    "availStatus": 1
  },
  {
    "movie": "Maa Inti Bangaaram [2D | Telugu]",
    "rawTitle": "Maa Inti Bangaaram",
    "lang": "Telugu",
    "format": "2D",
    "venue": "Srinivasa Theatre: Vuyyuru",
    "chain": "Justickets",
    "city": "Unknown",
    "state": "Unknown",
    "time": "2026-06-21 09:30 PM",
    "audi": "",
    "sessionId": "10016",
    "totalSeats": 383,
    "availableSeats": 255,
    "soldSeats": 128,
    "grossRevenue": 10100,
    "source": "BMS",
    "availStatus": 1
  },
  {
    "movie": "Peddi [2D | Telugu]",
    "rawTitle": "Peddi",
    "lang": "Telugu",
    "format": "2D",
    "venue": "Shanthi Theater A/C 2K Dolby: Vuyyuru",
    "chain": "Shanthi Theater A/C 2K Dolby: Vuyyuru",
    "city": "Unknown",
    "state": "Unknown",
    "time": "2026-06-21 09:30 PM",
    "audi": "",
    "sessionId": "11077",
    "totalSeats": 54,
    "availableSeats": 54,
    "soldSeats": 0,
    "grossRevenue": 0,
    "source": "BMS",
    "availStatus": 1
  },
  {
    "movie": "Vanda Devullu [2D | Telugu]",
    "rawTitle": "Vanda Devullu",
    "lang": "Telugu",
    "format": "2D",
    "venue": "Sai Mahal Theater: Vuyyuru",
    "chain": "Sai Mahal Theater: Vuyyuru",
    "city": "Unknown",
    "state": "Unknown",
    "time": "2026-06-21 09:30 PM",
    "audi": "",
    "sessionId": "15537",
    "totalSeats": 62,
    "availableSeats": 62,
    "soldSeats": 0,
    "grossRevenue": 0,
    "source": "BMS",
    "availStatus": 1
  },
  {
    "movie": "Cocktail 2 [2D | Hindi]",
    "rawTitle": "Cocktail 2",
    "lang": "Hindi",
    "format": "2D",
    "venue": "Connplex Cinemas: Sangamner",
    "chain": "Connplex Cinemas Ltd",
    "city": "Unknown",
    "state": "Unknown",
    "time": "2026-06-21 10:15 PM",
    "audi": "DOLBY 7.1",
    "sessionId": "2911",
    "totalSeats": 134,
    "availableSeats": 131,
    "soldSeats": 3,
    "grossRevenue": 900,
    "source": "BMS",
    "availStatus": 1
  },
  {
    "movie": "Ghabadkund [2D | Marathi]",
    "rawTitle": "Ghabadkund",
    "lang": "Marathi",
    "format": "2D",
    "venue": "Connplex Cinemas: Sangamner",
    "chain": "Connplex Cinemas Ltd",
    "city": "Unknown",
    "state": "Unknown",
    "time": "2026-06-21 09:30 PM",
    "audi": "DOLBY 7.1",
    "sessionId": "2926",
    "totalSeats": 134,
    "availableSeats": 123,
    "soldSeats": 11,
    "grossRevenue": 3650,
    "source": "BMS",
    "availStatus": 1
  },
  {
    "movie": "Peddi [2D | Hindi]",
    "rawTitle": "Peddi",
    "lang": "Hindi",
    "format": "2D",
    "venue": "Chitra Cinema: Satana",
    "chain": "Chitra Cinema, Satana",
    "city": "Unknown",
    "state": "Unknown",
    "time": "2026-06-21 09:30 PM",
    "audi": "",
    "sessionId": "82578",
    "totalSeats": 495,
    "availableSeats": 495,
    "soldSeats": 0,
    "grossRevenue": 0,
    "source": "BMS",
    "availStatus": 1
  },
  {
    "movie": "Cocktail 2 [2D | Hindi]",
    "rawTitle": "Cocktail 2",
    "lang": "Hindi",
    "format": "2D",
    "venue": "Sharda Cinema: Sukma",
    "chain": "Sharda Cinema",
    "city": "Unknown",
    "state": "Unknown",
    "time": "2026-06-21 08:45 PM",
    "audi": "",
    "sessionId": "98860",
    "totalSeats": 169,
    "availableSeats": 169,
    "soldSeats": 0,
    "grossRevenue": 0,
    "source": "BMS",
    "availStatus": 1
  },
  {
    "movie": "Maa Inti Bangaaram [2D | Telugu]",
    "rawTitle": "Maa Inti Bangaaram",
    "lang": "Telugu",
    "format": "2D",
    "venue": "SreeKanya Theatre 4K Dolby Atmos: Rly New Colony",
    "chain": "Sri Kanyaka Parameshwari Picture Palace",
    "city": "Unknown",
    "state": "Unknown",
    "time": "2026-06-21 09:45 PM",
    "audi": "JBL-4K Atmos",
    "sessionId": "1112",
    "totalSeats": 595,
    "availableSeats": 447,
    "soldSeats": 148,
    "grossRevenue": 20650,
    "source": "BMS",
    "availStatus": 1
  },
  {
    "movie": "Vanda Devullu [2D | Telugu]",
    "rawTitle": "Vanda Devullu",
    "lang": "Telugu",
    "format": "2D",
    "venue": "Aruna Picture Palace 2K A/C PAM",
    "chain": "Justickets",
    "city": "Unknown",
    "state": "Unknown",
    "time": "2026-06-21 09:30 PM",
    "audi": "",
    "sessionId": "990",
    "totalSeats": 808,
    "availableSeats": 808,
    "soldSeats": 0,
    "grossRevenue": 0,
    "source": "BMS",
    "availStatus": 1
  },
  {
    "movie": "Transfer Trimurthulu [2D | Telugu]",
    "rawTitle": "Transfer Trimurthulu",
    "lang": "Telugu",
    "format": "2D",
    "venue": "Srinivasa Theater A/c 2K Dolby: Yemmiganur",
    "chain": "Srinivasa Theater A/c 2K Dolby: Yemmiganur",
    "city": "Unknown",
    "state": "Unknown",
    "time": "2026-06-21 10:00 PM",
    "audi": "",
    "sessionId": "10666",
    "totalSeats": 385,
    "availableSeats": 385,
    "soldSeats": 0,
    "grossRevenue": 0,
    "source": "BMS",
    "availStatus": 1
  },
  {
    "movie": "Peddi [2D | Telugu]",
    "rawTitle": "Peddi",
    "lang": "Telugu",
    "format": "2D",
    "venue": "Gayathri Theater 2K Dolby: Yerragondapalem",
    "chain": "Gayathri Theater A/c 2K Dolby: Yerragondapalem",
    "city": "Unknown",
    "state": "Unknown",
    "time": "2026-06-21 10:00 PM",
    "audi": "",
    "sessionId": "11099",
    "totalSeats": 234,
    "availableSeats": 234,
    "soldSeats": 0,
    "grossRevenue": 0,
    "source": "BMS",
    "availStatus": 1
  },
  {
    "movie": "Blast Zone [2D | Telugu]",
    "rawTitle": "Blast Zone",
    "lang": "Telugu",
    "format": "2D",
    "venue": "SunMax - Chandra Mahal A/c Dts: Srikakulam",
    "chain": "SunMax - Chandra Mahal A/c Dts",
    "city": "Unknown",
    "state": "Unknown",
    "time": "2026-06-21 09:45 PM",
    "audi": "",
    "sessionId": "23529",
    "totalSeats": 60,
    "availableSeats": 60,
    "soldSeats": 0,
    "grossRevenue": 0,
    "source": "BMS",
    "availStatus": 1
  },
  {
    "movie": "Balan: The Boy [2D | Tamil]",
    "rawTitle": "Balan: The Boy",
    "lang": "Tamil",
    "format": "2D",
    "venue": "Shreepathy Cinemas (PLF) Atmos RGB Laser:Thanjavur",
    "chain": "The Shreepathy Lodge",
    "city": "Unknown",
    "state": "Unknown",
    "time": "2026-06-21 10:15 PM",
    "audi": "2K DOLBY 7.1",
    "sessionId": "2517",
    "totalSeats": 177,
    "availableSeats": 177,
    "soldSeats": 0,
    "grossRevenue": 0,
    "source": "BMS",
    "availStatus": 1
  },
  {
    "movie": "Nooru Sami [2D | Tamil]",
    "rawTitle": "Nooru Sami",
    "lang": "Tamil",
    "format": "2D",
    "venue": "Shreepathy Cinemas (PLF) Atmos RGB Laser:Thanjavur",
    "chain": "The Shreepathy Lodge",
    "city": "Unknown",
    "state": "Unknown",
    "time": "2026-06-21 10:00 PM",
    "audi": "4K DOLBY ATMOS",
    "sessionId": "2513",
    "totalSeats": 483,
    "availableSeats": 481,
    "soldSeats": 2,
    "grossRevenue": 300,
    "source": "BMS",
    "availStatus": 1
  },
  {
    "movie": "Nooru Sami [2D | Tamil]",
    "rawTitle": "Nooru Sami",
    "lang": "Tamil",
    "format": "2D",
    "venue": "Starline Cinemas: Thanjavur",
    "chain": "Starline Cinemas Private Limited",
    "city": "Unknown",
    "state": "Unknown",
    "time": "2026-06-21 10:40 PM",
    "audi": "",
    "sessionId": "4889",
    "totalSeats": 237,
    "availableSeats": 230,
    "soldSeats": 7,
    "grossRevenue": 1650,
    "source": "BMS",
    "availStatus": 1
  },
  {
    "movie": "Engal Thangam [2D | Tamil]",
    "rawTitle": "Engal Thangam",
    "lang": "Tamil",
    "format": "2D",
    "venue": "Starline Cinemas: Thanjavur",
    "chain": "Starline Cinemas Private Limited",
    "city": "Unknown",
    "state": "Unknown",
    "time": "2026-06-21 10:15 PM",
    "audi": "",
    "sessionId": "4890",
    "totalSeats": 312,
    "availableSeats": 308,
    "soldSeats": 4,
    "grossRevenue": 1000,
    "source": "BMS",
    "availStatus": 1
  },
  {
    "movie": "Cocktail 2 [2D | Hindi]",
    "rawTitle": "Cocktail 2",
    "lang": "Hindi",
    "format": "2D",
    "venue": "Starline Cinemas: Thanjavur",
    "chain": "Starline Cinemas Private Limited",
    "city": "Unknown",
    "state": "Unknown",
    "time": "2026-06-21 09:45 PM",
    "audi": "",
    "sessionId": "4887",
    "totalSeats": 227,
    "availableSeats": 221,
    "soldSeats": 6,
    "grossRevenue": 1200,
    "source": "BMS",
    "availStatus": 1
  },
  {
    "movie": "Cocktail 2 [2D | Hindi]",
    "rawTitle": "Cocktail 2",
    "lang": "Hindi",
    "format": "2D",
    "venue": "Chhotu Maharaj Cine Cafe:Unnao",
    "chain": "K Sera Sera Box Office Pvt. Ltd.",
    "city": "Unknown",
    "state": "Unknown",
    "time": "2026-06-21 08:00 PM",
    "audi": "",
    "sessionId": "2064",
    "totalSeats": 135,
    "availableSeats": 135,
    "soldSeats": 0,
    "grossRevenue": 0,
    "source": "BMS",
    "availStatus": 1
  }
]